nlp_preprocess_toolkit_utils/__init__.py
nlp_preprocess_toolkit_utils/preprocess.py
nlp_preprocess_toolkit_utils-0.2.1.dist-info/LICENSE
nlp_preprocess_toolkit_utils-0.2.1.dist-info/METADATA
nlp_preprocess_toolkit_utils-0.2.1.dist-info/WHEEL
nlp_preprocess_toolkit_utils-0.2.1.dist-info/top_level.txt
nlp_preprocess_toolkit_utils-0.2.1.dist-info/RECORD
