Metadata-Version: 2.1
Name: nlp_preprocess_toolkit_utils
Version: 0.2.1
Summary: A package for NLP preprocessing and word cloud generation
Home-page: https://github.com/rubansendhur/nlp_preprocess_toolkit
Author: Rubansendhur
Author-email: rubansendhur78409@gmail.com
Classifier: Programming Language :: Python :: 3
Classifier: License :: OSI Approved :: MIT License
Classifier: Operating System :: OS Independent
Requires-Python: >=3.6
License-File: LICENSE
Requires-Dist: pandas
Requires-Dist: requests
Requires-Dist: wordcloud
Requires-Dist: nltk
Requires-Dist: matplotlib
